lkh/__init__.py
lkh/problems.py
tsplib95/__init__.py
tsplib95/bisep.py
tsplib95/cli.py
tsplib95/distances.py
tsplib95/exceptions.py
tsplib95/fields.py
tsplib95/loaders.py
tsplib95/matrix.py
tsplib95/models.py
tsplib95/transformers.py
tsplib95/utils.py
lkh-2.0.0.dist-info/LICENSE.txt
lkh-2.0.0.dist-info/METADATA
lkh-2.0.0.dist-info/WHEEL
lkh-2.0.0.dist-info/RECORD
