Metadata-Version: 2.1
Name: lkh
Version: 2.0.0
Summary: Super simple Python wrapper for LKH-3
License: DBAD
Author: Ben Hudson
Author-email: benhudson@fastmail.com
Requires-Python: >=3.3,<4.0
Classifier: License :: Other/Proprietary License
Classifier: Programming Language :: Python :: 3
Classifier: Programming Language :: Python :: 3.4
Classifier: Programming Language :: Python :: 3.5
Classifier: Programming Language :: Python :: 3.6
Classifier: Programming Language :: Python :: 3.7
Classifier: Programming Language :: Python :: 3.8
Classifier: Programming Language :: Python :: 3.9
Classifier: Programming Language :: Python :: 3.10
Classifier: Programming Language :: Python :: 3.11
Requires-Dist: Click (>=6.0,<7.0)
Requires-Dist: Deprecated (>=1.2.9,<1.3.0)
Requires-Dist: networkx (>=2.1,<3.0)
Requires-Dist: tabulate (>=0.8.7,<0.9.0)
